{
  "station" : "GMW00035104",
  "zeitraum" : "1949-1959",
  "jahreszeiten" : {
    "Winter_1951_1952" : {
      "minTemp" : -8.3,
      "maxTemp" : 10.6
    },
    "Sommer_1950" : {
      "minTemp" : 9.4,
      "maxTemp" : 33.3
    },
    "Sommer_1952" : {
      "minTemp" : 7.8,
      "maxTemp" : 33.9
    },
    "Winter_1948_1949" : {
      "minTemp" : -6.1,
      "maxTemp" : 13.9
    },
    "Sommer_1951" : {
      "minTemp" : 7.8,
      "maxTemp" : 32.8
    },
    "Sommer_1954" : {
      "minTemp" : 9.4,
      "maxTemp" : 34.4
    },
    "Sommer_1953" : {
      "minTemp" : 7.8,
      "maxTemp" : 31.7
    },
    "Sommer_1955" : {
      "minTemp" : 6.7,
      "maxTemp" : 30.0
    },
    "Winter_1952_1953" : {
      "minTemp" : -15.6,
      "maxTemp" : 14.4
    },
    "Herbst_1954" : {
      "minTemp" : -6.1,
      "maxTemp" : 30.6
    },
    "Sommer_1949" : {
      "minTemp" : 5.6,
      "maxTemp" : 35.6
    },
    "Herbst_1951" : {
      "minTemp" : 1.1,
      "maxTemp" : 30.6
    },
    "Frühling_1949" : {
      "minTemp" : -11.1,
      "maxTemp" : 29.4
    },
    "Herbst_1950" : {
      "minTemp" : -1.1,
      "maxTemp" : 27.8
    },
    "Herbst_1953" : {
      "minTemp" : -6.1,
      "maxTemp" : 30.6
    },
    "Herbst_1952" : {
      "minTemp" : -6.7,
      "maxTemp" : 23.3
    },
    "Winter_1950_1951" : {
      "minTemp" : -13.9,
      "maxTemp" : 12.2
    },
    "Winter_1953_1954" : {
      "minTemp" : -18.9,
      "maxTemp" : 14.4
    },
    "Frühling_1952" : {
      "minTemp" : -6.1,
      "maxTemp" : 25.6
    },
    "Frühling_1953" : {
      "minTemp" : -3.9,
      "maxTemp" : 30.6
    },
    "Frühling_1950" : {
      "minTemp" : -10.0,
      "maxTemp" : 31.7
    },
    "Frühling_1951" : {
      "minTemp" : -7.2,
      "maxTemp" : 27.2
    },
    "Herbst_1949" : {
      "minTemp" : -5.6,
      "maxTemp" : 29.4
    },
    "Winter_1954_1955" : {
      "minTemp" : -14.4,
      "maxTemp" : 11.7
    },
    "Frühling_1954" : {
      "minTemp" : -1.7,
      "maxTemp" : 26.1
    },
    "Winter_1949_1950" : {
      "minTemp" : -11.7,
      "maxTemp" : 15.6
    },
    "Frühling_1955" : {
      "minTemp" : -10.0,
      "maxTemp" : 29.4
    }
  }
}